__init__.py
memv.py
setup.py
utils/__init__.py
utils/utils.py
memv_package_nhunh-0.0.1.dist-info/METADATA
memv_package_nhunh-0.0.1.dist-info/WHEEL
memv_package_nhunh-0.0.1.dist-info/licenses/LICENSE
memv_package_nhunh-0.0.1.dist-info/RECORD
