Metadata-Version: 2.1
Name: memv_package_nhunh
Version: 0.0.1
Summary: Visualize memory usage
Author-email: nhunh <coinhu1995@gmail.com>
License-File: LICENSE
Classifier: License :: OSI Approved :: MIT License
Classifier: Operating System :: OS Independent
Classifier: Programming Language :: Python :: 3
Requires-Python: >=3.7
